LICENSE
MANIFEST.in
README.md
requirements.txt
setup.py
er_xpcspy.egg-info/PKG-INFO
er_xpcspy.egg-info/SOURCES.txt
er_xpcspy.egg-info/dependency_links.txt
er_xpcspy.egg-info/entry_points.txt
er_xpcspy.egg-info/requires.txt
er_xpcspy.egg-info/top_level.txt
xpcspy/__init__.py
xpcspy/../_agent.js
xpcspy/console/__init__.py
xpcspy/console/cli.py
xpcspy/lib/__init__.py
xpcspy/lib/types.py
xpcspy/utils/__init__.py
xpcspy/utils/agent.py