Metadata-Version: 2.1
Name: er-xpcspy
Version: 0.8.4
Summary: XPC message interception and more
Home-page: https://github.com/EricRabil/xpcspy
Author: hot3eed
Author-email: hot3eed@gmail.com
License: Apache-2.0
Keywords: macos,ios,xnu,xpc,frida
License-File: LICENSE
